README.rst
setup.py
urwid_stackedwidget.py
urwid_stackedwidget.egg-info/PKG-INFO
urwid_stackedwidget.egg-info/SOURCES.txt
urwid_stackedwidget.egg-info/dependency_links.txt
urwid_stackedwidget.egg-info/requires.txt
urwid_stackedwidget.egg-info/top_level.txt